<?xml version="1.0"?>
<gconf>
	<entry name="next_tab" mtime="1402333311" type="string">
		<stringvalue>&lt;Alt&gt;Right</stringvalue>
	</entry>
	<entry name="prev_tab" mtime="1402333306" type="string">
		<stringvalue>&lt;Alt&gt;Left</stringvalue>
	</entry>
	<entry name="paste" mtime="1402333294" type="string">
		<stringvalue>&lt;Primary&gt;v</stringvalue>
	</entry>
	<entry name="copy" mtime="1402333291" type="string">
		<stringvalue>&lt;Primary&gt;c</stringvalue>
	</entry>
	<entry name="close_window" mtime="1402333288" type="string">
		<stringvalue>&lt;Primary&gt;q</stringvalue>
	</entry>
	<entry name="close_tab" mtime="1402333286" type="string">
		<stringvalue>&lt;Primary&gt;w</stringvalue>
	</entry>
	<entry name="new_window" mtime="1402333283" type="string">
		<stringvalue>&lt;Primary&gt;n</stringvalue>
	</entry>
	<entry name="new_tab" mtime="1402333279" type="string">
		<stringvalue>&lt;Primary&gt;t</stringvalue>
	</entry>
</gconf>
